README.md
setup.py
tests/__init__.py
tests/test_wibble.py
travisty/__init__.py
travisty/__main__.py
travisty/wibble.py
travisty.egg-info/PKG-INFO
travisty.egg-info/SOURCES.txt
travisty.egg-info/dependency_links.txt
travisty.egg-info/entry_points.txt
travisty.egg-info/requires.txt
travisty.egg-info/top_level.txt