Metadata-Version: 1.1
Name: travisty
Version: 0.0.2
Summary: Repo for testing out travis
Home-page: https://github.com/martinghunt/travisty
Author: Martin Hunt
Author-email: mhunt@ebi.ac.uk
License: MIT
Platform: UNKNOWN
Classifier: Development Status :: 4 - Beta
Classifier: Topic :: Scientific/Engineering :: Bio-Informatics
Classifier: Programming Language :: Python :: 3 :: Only
Classifier: License :: OSI Approved :: MIT License
